pdocs/__init__.py
pdocs/_version.py
pdocs/api.py
pdocs/cli.py
pdocs/defaults.py
pdocs/doc.py
pdocs/extract.py
pdocs/html_helpers.py
pdocs/logo.py
pdocs/render.py
pdocs/static.py
pdocs/templates/LICENSE
pdocs/templates/README.md
pdocs/templates/css.mako
pdocs/templates/html_frame.mako
pdocs/templates/html_index.mako
pdocs/templates/html_module.mako
pdocs/templates/text.mako
pdocs-1.1.1.dist-info/entry_points.txt
pdocs-1.1.1.dist-info/LICENSE
pdocs-1.1.1.dist-info/WHEEL
pdocs-1.1.1.dist-info/METADATA
pdocs-1.1.1.dist-info/RECORD
