Metadata-Version: 2.1
Name: pdocs
Version: 1.1.1
Summary: A simple program and library to auto generate API documentation for Python modules.
License: MIT
Author: Timothy Crosley
Author-email: timothy.crosley@gmail.com
Requires-Python: >=3.6,<4.0
Classifier: License :: OSI Approved :: MIT License
Classifier: Programming Language :: Python :: 3
Classifier: Programming Language :: Python :: 3.6
Classifier: Programming Language :: Python :: 3.7
Classifier: Programming Language :: Python :: 3.8
Classifier: Programming Language :: Python :: 3.9
Requires-Dist: Mako (>=1.1,<2.0)
Requires-Dist: Markdown (>=3.0.0,<4.0.0)
Requires-Dist: dataclasses (>=0.7,<0.8); python_version >= "3.6" and python_version < "3.7"
Requires-Dist: docstring_parser (>=0.7.2,<0.8.0)
Requires-Dist: hug (>=2.6,<3.0)
